{
  "elements": {
    "nodes": [
      {
        "data": {
          "id": "n1"
        },
        "position": {
          "x": 505.6603332140785,
          "y": 119.69786341517957
        },
        "group": "nodes",
        "removed": false,
        "selected": false,
        "selectable": true,
        "locked": false,
        "grabbable": true,
        "pannable": false,
        "classes": ""
      },
      {
        "data": {
          "id": "n2"
        },
        "position": {
          "x": 537.0165314067724,
          "y": 581.1138547430785
        },
        "group": "nodes",
        "removed": false,
        "selected": false,
        "selectable": true,
        "locked": false,
        "grabbable": true,
        "pannable": false,
        "classes": ""
      },
      {
        "data": {
          "id": "n3",
          "parent": "n4"
        },
        "position": {
          "x": 171.3188196581524,
          "y": 405.50975326081215
        },
        "group": "nodes",
        "removed": false,
        "selected": false,
        "selectable": true,
        "locked": false,
        "grabbable": true,
        "pannable": false,
        "classes": ""
      },
      {
        "data": {
          "id": "n5",
          "parent": "n4"
        },
        "position": {
          "x": 198.33572050133455,
          "y": 323.2140804925652
        },
        "group": "nodes",
        "removed": false,
        "selected": false,
        "selectable": true,
        "locked": false,
        "grabbable": true,
        "pannable": false,
        "classes": ""
      },
      {
        "data": {
          "id": "n6"
        },
        "position": {
          "x": 268.9567745501894,
          "y": 504.754332485224
        },
        "group": "nodes",
        "removed": false,
        "selected": false,
        "selectable": true,
        "locked": false,
        "grabbable": true,
        "pannable": false,
        "classes": ""
      },
      {
        "data": {
          "id": "n7",
          "parent": "n4"
        },
        "position": {
          "x": 70.93306195427135,
          "y": 398.59826147606174
        },
        "group": "nodes",
        "removed": false,
        "selected": false,
        "selectable": true,
        "locked": false,
        "grabbable": true,
        "pannable": false,
        "classes": ""
      },
      {
        "data": {
          "id": "n8"
        },
        "position": {
          "x": 252.52962492339793,
          "y": 171.05582339771996
        },
        "group": "nodes",
        "removed": false,
        "selected": false,
        "selectable": true,
        "locked": false,
        "grabbable": true,
        "pannable": false,
        "classes": ""
      },
      {
        "data": {
          "id": "n9",
          "parent": "n1"
        },
        "position": {
          "x": 450.4301399146409,
          "y": 141.16432393407928
        },
        "group": "nodes",
        "removed": false,
        "selected": false,
        "selectable": true,
        "locked": false,
        "grabbable": true,
        "pannable": false,
        "classes": ""
      },
      {
        "data": {
          "id": "n4"
        },
        "position": {
          "x": 119.16786025066727,
          "y": 316.29527313778897
        },
        "group": "nodes",
        "removed": false,
        "selected": false,
        "selectable": true,
        "locked": false,
        "grabbable": true,
        "pannable": false,
        "classes": ""
      },
      {
        "data": {
          "id": "n10",
          "parent": "n1"
        },
        "position": {
          "x": 483.72781264274784,
          "y": 214.39572683035914
        },
        "group": "nodes",
        "removed": false,
        "selected": false,
        "selectable": true,
        "locked": false,
        "grabbable": true,
        "pannable": false,
        "classes": ""
      },
      
      {
        "data": {
          "id": "n11",
          "parent": "1"
        },
        "position": {
          "x": 537.111715668942,
          "y": 127.7515294424245
        },
        "group": "nodes",
        "removed": false,
        "selected": false,
        "selectable": true,
        "locked": false,
        "grabbable": true,
        "pannable": false,
        "classes": ""
      },
      {
        "data": {
          "id": "n12",
          "parent": "n4"
        },
        "position": {
          "x": 125.50792802158503,
          "y": 242.0807930147658
        },
        "group": "nodes",
        "removed": false,
        "selected": false,
        "selectable": true,
        "locked": false,
        "grabbable": true,
        "pannable": false,
        "classes": ""
      },
      {
        "data": {
          "id": "n13",
          "parent": "n4"
        },
        "position": {
          "x": 40,
          "y": 309.02741476495913
        },
        "group": "nodes",
        "removed": false,
        "selected": false,
        "selectable": true,
        "locked": false,
        "grabbable": true,
        "pannable": false,
        "classes": ""
      },
      {
        "data": {
          "id": "n14",
          "parent": "n1"
        },
        "position": {
          "x": 560.8905265135161,
          "y": 40
        },
        "group": "nodes",
        "removed": false,
        "selected": false,
        "selectable": true,
        "locked": false,
        "grabbable": true,
        "pannable": false,
        "classes": ""
      },
      {
        "data": {
          "id": "n15"
        },
        "position": {
          "x": 615.5572965020281,
          "y": 383.76549706019483
        },
        "group": "nodes",
        "removed": false,
        "selected": false,
        "selectable": true,
        "locked": false,
        "grabbable": true,
        "pannable": false,
        "classes": ""
      },
      {
        "data": {
          "id": "n16"
        },
        "position": {
          "x": 527.1279765714255,
          "y": 387.12777058435455
        },
        "group": "nodes",
        "removed": false,
        "selected": false,
        "selectable": true,
        "locked": false,
        "grabbable": true,
        "pannable": false,
        "classes": ""
      },
      {
        "data": {
          "id": "n17"
        },
        "position": {
          "x": 448.8574467618504,
          "y": 327.65839878175626
        },
        "group": "nodes",
        "removed": false,
        "selected": false,
        "selectable": true,
        "locked": false,
        "grabbable": true,
        "pannable": false,
        "classes": ""
      },
      {
        "data": {
          "id": "n18"
        },
        "position": {
          "x": 297.9897560888269,
          "y": 428.24243401553423
        },
        "group": "nodes",
        "removed": false,
        "selected": false,
        "selectable": true,
        "locked": false,
        "grabbable": true,
        "pannable": false,
        "classes": ""
      },
      {
        "data": {
          "id": "n19"
        },
        "position": {
          "x": 371.3281070138712,
          "y": 367.3888774986821
        },
        "group": "nodes",
        "removed": false,
        "selected": false,
        "selectable": true,
        "locked": false,
        "grabbable": true,
        "pannable": false,
        "classes": ""
      },
      {
        "data": {
          "id": "n20"
        },
        "position": {
          "x": 384.1062563531192,
          "y": 242.01104255634556
        },
        "group": "nodes",
        "removed": false,
        "selected": false,
        "selectable": true,
        "locked": false,
        "grabbable": true,
        "pannable": false,
        "classes": ""
      },
      {
        "data": {
          "id": "n21"
        },
        "position": {
          "x": 290.79923857006713,
          "y": 348.06744207046023
        },
        "group": "nodes",
        "removed": false,
        "selected": false,
        "selectable": true,
        "locked": false,
        "grabbable": true,
        "pannable": false,
        "classes": ""
      },
      {
        "data": {
          "id": "n22"
        },
        "position": {
          "x": 575.221133026984,
          "y": 310.084034588415
        },
        "group": "nodes",
        "removed": false,
        "selected": false,
        "selectable": true,
        "locked": false,
        "grabbable": true,
        "pannable": false,
        "classes": ""
      },
      {
        "data": {
          "id": "n23"
        },
        "position": {
          "x": 303.1344583521817,
          "y": 257.20291637960264
        },
        "group": "nodes",
        "removed": false,
        "selected": false,
        "selectable": true,
        "locked": false,
        "grabbable": true,
        "pannable": false,
        "classes": ""
      },
      
      {
        "data": {
          "id": "n24",
          "parent": "n25"
        },
        "position": {
          "x": 610.4271034214296,
          "y": 682.3735269645749
        },
        "group": "nodes",
        "removed": false,
        "selected": false,
        "selectable": true,
        "locked": false,
        "grabbable": true,
        "pannable": false,
        "classes": ""
      },
      {
        "data": {
          "id": "n26",
          "parent": "n25"
        },
        "position": {
          "x": 602.7134281327942,
          "y": 509.354182521582
        },
        "group": "nodes",
        "removed": false,
        "selected": false,
        "selectable": true,
        "locked": false,
        "grabbable": true,
        "pannable": false,
        "classes": ""
      },
      {
        "data": {
          "id": "n27",
          "parent": "n25"
        },
        "position": {
          "x": 604.1287984230876,
          "y": 596.1721543696901
        },
        "group": "nodes",
        "removed": false,
        "selected": false,
        "selectable": true,
        "locked": false,
        "grabbable": true,
        "pannable": false,
        "classes": ""
      },
      {
        "data": {
          "id": "n28",
          "parent": "n25"
        },
        "position": {
          "x": 521.7048631289804,
          "y": 548.7060779638095
        },
        "group": "nodes",
        "removed": false,
        "selected": false,
        "selectable": true,
        "locked": false,
        "grabbable": true,
        "pannable": false,
        "classes": ""
      },
      {
        "data": {
          "id": "n29",
          "parent": "n25"
        },
        "position": {
          "x": 685.0997634867981,
          "y": 638.4847047073804
        },
        "group": "nodes",
        "removed": false,
        "selected": false,
        "selectable": true,
        "locked": false,
        "grabbable": true,
        "pannable": false,
        "classes": ""
      },
      {
        "data": {
          "id": "n25",
          "parent": "n2"
        },
        "position": {
          "x": 603.4023133078892,
          "y": 588.3638547430785
        },
        "group": "nodes",
        "removed": false,
        "selected": false,
        "selectable": true,
        "locked": false,
        "grabbable": true,
        "pannable": false,
        "classes": ""
      },
      {
        "data": {
          "id": "n30",
          "parent": "n2"
        },
        "position": {
          "x": 402.020351839961,
          "y": 505.44583826639274
        },
        "group": "nodes",
        "removed": false,
        "selected": false,
        "selectable": true,
        "locked": false,
        "grabbable": true,
        "pannable": false,
        "classes": ""
      },
      {
        "data": {
          "id": "n31",
          "parent": "n2"
        },
        "position": {
          "x": 377.4332993267466,
          "y": 588.9777502020386
        },
        "group": "nodes",
        "removed": false,
        "selected": false,
        "selectable": true,
        "locked": false,
        "grabbable": true,
        "pannable": false,
        "classes": ""
      },
      {
        "data": {
          "id": "n32",
          "parent": "n2"
        },
        "position": {
          "x": 378.963014567301,
          "y": 673.8690459244726
        },
        "group": "nodes",
        "removed": false,
        "selected": false,
        "selectable": true,
        "locked": false,
        "grabbable": true,
        "pannable": false,
        "classes": ""
      }
    ],
    "edges": [
      {
        "data": {
          "source": "n15",
          "target": "n26",
          "id": "e1"
        },
        "position": {
          "x": 0,
          "y": 0
        },
        "group": "edges",
        "removed": false,
        "selected": false,
        "selectable": true,
        "locked": false,
        "grabbable": true,
        "pannable": true,
        "classes": ""
      },
      
      
      {
        "data": {
          "source": "n5",
          "target": "n3",
          "id": "e2"
        },
        "position": {
          "x": 0,
          "y": 0
        },
        "group": "edges",
        "removed": false,
        "selected": false,
        "selectable": true,
        "locked": false,
        "grabbable": true,
        "pannable": true,
        "classes": ""
      },
      {
        "data": {
          "source": "n9",
          "target": "n10",
          "id": "e3"
        },
        "position": {
          "x": 0,
          "y": 0
        },
        "group": "edges",
        "removed": false,
        "selected": false,
        "selectable": true,
        "locked": false,
        "grabbable": true,
        "pannable": true,
        "classes": ""
      },
      {
        "data": {
          "source": "n12",
          "target": "n13",
          "id": "e4"
        },
        "position": {
          "x": 0,
          "y": 0
        },
        "group": "edges",
        "removed": false,
        "selected": false,
        "selectable": true,
        "locked": false,
        "grabbable": true,
        "pannable": true,
        "classes": ""
      },
      {
        "data": {
          "source": "n6",
          "target": "n3",
          "id": "e5"
        },
        "position": {
          "x": 0,
          "y": 0
        },
        "group": "edges",
        "removed": false,
        "selected": false,
        "selectable": true,
        "locked": false,
        "grabbable": true,
        "pannable": true,
        "classes": ""
      },
      {
        "data": {
          "source": "n3",
          "target": "n7",
          "id": "e6"
        },
        "position": {
          "x": 0,
          "y": 0
        },
        "group": "edges",
        "removed": false,
        "selected": false,
        "selectable": true,
        "locked": false,
        "grabbable": true,
        "pannable": true,
        "classes": ""
      },
      {
        "data": {
          "source": "n6",
          "target": "n18",
          "id": "e7"
        },
        "position": {
          "x": 0,
          "y": 0
        },
        "group": "edges",
        "removed": false,
        "selected": false,
        "selectable": true,
        "locked": false,
        "grabbable": true,
        "pannable": true,
        "classes": ""
      },
      {
        "data": {
          "source": "n17",
          "target": "n20",
          "id": "e8"
        },
        "position": {
          "x": 0,
          "y": 0
        },
        "group": "edges",
        "removed": false,
        "selected": false,
        "selectable": true,
        "locked": false,
        "grabbable": true,
        "pannable": true,
        "classes": ""
      },
      {
        "data": {
          "source": "n23",
          "target": "n8",
          "id": "e9"
        },
        "position": {
          "x": 0,
          "y": 0
        },
        "group": "edges",
        "removed": false,
        "selected": false,
        "selectable": true,
        "locked": false,
        "grabbable": true,
        "pannable": true,
        "classes": ""
      },
      {
        "data": {
          "source": "n14",
          "target": "n11",
          "id": "e10"
        },
        "position": {
          "x": 0,
          "y": 0
        },
        "group": "edges",
        "removed": false,
        "selected": false,
        "selectable": true,
        "locked": false,
        "grabbable": true,
        "pannable": true,
        "classes": ""
      },
      
      
      {
        "data": {
          "source": "n21",
          "target": "n23",
          "id": "e11"
        },
        "position": {
          "x": 0,
          "y": 0
        },
        "group": "edges",
        "removed": false,
        "selected": false,
        "selectable": true,
        "locked": false,
        "grabbable": true,
        "pannable": true,
        "classes": ""
      },
      
      {
        "data": {
          "source": "n22",
          "target": "n1",
          "id": "e12"
        },
        "position": {
          "x": 0,
          "y": 0
        },
        "group": "edges",
        "removed": false,
        "selected": false,
        "selectable": true,
        "locked": false,
        "grabbable": true,
        "pannable": true,
        "classes": ""
      },
      {
        "data": {
          "source": "n15",
          "target": "n22",
          "id": "ne13"
        },
        "position": {
          "x": 0,
          "y": 0
        },
        "group": "edges",
        "removed": false,
        "selected": false,
        "selectable": true,
        "locked": false,
        "grabbable": true,
        "pannable": true,
        "classes": ""
      },
      {
        "data": {
          "source": "n11",
          "target": "n9",
          "id": "ne14"
        },
        "position": {
          "x": 0,
          "y": 0
        },
        "group": "edges",
        "removed": false,
        "selected": false,
        "selectable": true,
        "locked": false,
        "grabbable": true,
        "pannable": true,
        "classes": ""
      },
      {
        "data": {
          "source": "n16",
          "target": "n2",
          "id": "e15"
        },
        "position": {
          "x": 0,
          "y": 0
        },
        "group": "edges",
        "removed": false,
        "selected": false,
        "selectable": true,
        "locked": false,
        "grabbable": true,
        "pannable": true,
        "classes": ""
      },
      
      {
        "data": {
          "source": "n31",
          "target": "n32",
          "id": "e16"
        },
        "position": {
          "x": 0,
          "y": 0
        },
        "group": "edges",
        "removed": false,
        "selected": false,
        "selectable": true,
        "locked": false,
        "grabbable": true,
        "pannable": true,
        "classes": ""
      },
      {
        "data": {
          "source": "n20",
          "target": "n23",
          "id": "e17"
        },
        "position": {
          "x": 0,
          "y": 0
        },
        "group": "edges",
        "removed": false,
        "selected": false,
        "selectable": true,
        "locked": false,
        "grabbable": true,
        "pannable": true,
        "classes": ""
      },
      {
        "data": {
          "source": "n7",
          "target": "n13",
          "id": "e18"
        },
        "position": {
          "x": 0,
          "y": 0
        },
        "group": "edges",
        "removed": false,
        "selected": false,
        "selectable": true,
        "locked": false,
        "grabbable": true,
        "pannable": true,
        "classes": ""
      },
      {
        "data": {
          "source": "n23",
          "target": "n5",
          "id": "e19"
        },
        "position": {
          "x": 0,
          "y": 0
        },
        "group": "edges",
        "removed": false,
        "selected": false,
        "selectable": true,
        "locked": false,
        "grabbable": true,
        "pannable": true,
        "classes": ""
      },
      {
        "data": {
          "source": "n21",
          "target": "n3",
          "id": "e20"
        },
        "position": {
          "x": 0,
          "y": 0
        },
        "group": "edges",
        "removed": false,
        "selected": false,
        "selectable": true,
        "locked": false,
        "grabbable": true,
        "pannable": true,
        "classes": ""
      },
      
      {
        "data": {
          "source": "n10",
          "target": "n11",
          "id": "e21"
        },
        "position": {
          "x": 0,
          "y": 0
        },
        "group": "edges",
        "removed": false,
        "selected": false,
        "selectable": true,
        "locked": false,
        "grabbable": true,
        "pannable": true,
        "classes": ""
      },
      {
        "data": {
          "source": "n16",
          "target": "n22",
          "id": "e22"
        },
        "position": {
          "x": 0,
          "y": 0
        },
        "group": "edges",
        "removed": false,
        "selected": false,
        "selectable": true,
        "locked": false,
        "grabbable": true,
        "pannable": true,
        "classes": ""
      },
      {
        "data": {
          "source": "n8",
          "target": "n12",
          "id": "e23"
        },
        "position": {
          "x": 0,
          "y": 0
        },
        "group": "edges",
        "removed": false,
        "selected": false,
        "selectable": true,
        "locked": false,
        "grabbable": true,
        "pannable": true,
        "classes": ""
      },
      {
        "data": {
          "source": "n6",
          "target": "n2",
          "id": "e24"
        },
        "position": {
          "x": 0,
          "y": 0
        },
        "group": "edges",
        "removed": false,
        "selected": false,
        "selectable": true,
        "locked": false,
        "grabbable": true,
        "pannable": true,
        "classes": ""
      },
      {
        "data": {
          "source": "n9",
          "target": "n20",
          "id": "e25"
        },
        "position": {
          "x": 0,
          "y": 0
        },
        "group": "edges",
        "removed": false,
        "selected": false,
        "selectable": true,
        "locked": false,
        "grabbable": true,
        "pannable": true,
        "classes": ""
      },
      {
        "data": {
          "source": "n18",
          "target": "n21",
          "id": "e26"
        },
        "position": {
          "x": 0,
          "y": 0
        },
        "group": "edges",
        "removed": false,
        "selected": false,
        "selectable": true,
        "locked": false,
        "grabbable": true,
        "pannable": true,
        "classes": ""
      },
      {
        "data": {
          "source": "n21",
          "target": "n19",
          "id": "e27"
        },
        "position": {
          "x": 0,
          "y": 0
        },
        "group": "edges",
        "removed": false,
        "selected": false,
        "selectable": true,
        "locked": false,
        "grabbable": true,
        "pannable": true,
        "classes": ""
      },
      {
        "data": {
          "source": "n19",
          "target": "n17",
          "id": "e28"
        },
        "position": {
          "x": 0,
          "y": 0
        },
        "group": "edges",
        "removed": false,
        "selected": false,
        "selectable": true,
        "locked": false,
        "grabbable": true,
        "pannable": true,
        "classes": ""
      },
      {
        "data": {
          "source": "n17",
          "target": "n16",
          "id": "e29"
        },
        "position": {
          "x": 0,
          "y": 0
        },
        "group": "edges",
        "removed": false,
        "selected": false,
        "selectable": true,
        "locked": false,
        "grabbable": true,
        "pannable": true,
        "classes": ""
      },
      {
        "data": {
          "source": "n16",
          "target": "n15",
          "id": "e30"
        },
        "position": {
          "x": 0,
          "y": 0
        },
        "group": "edges",
        "removed": false,
        "selected": false,
        "selectable": true,
        "locked": false,
        "grabbable": true,
        "pannable": true,
        "classes": ""
      },
      {
        "data": {
          "source": "n27",
          "target": "n24",
          "id": "e31"
        },
        "position": {
          "x": 0,
          "y": 0
        },
        "group": "edges",
        "removed": false,
        "selected": false,
        "selectable": true,
        "locked": false,
        "grabbable": true,
        "pannable": true,
        "classes": ""
      },
      {
        "data": {
          "source": "n24",
          "target": "n29",
          "id": "e32"
        },
        "position": {
          "x": 0,
          "y": 0
        },
        "group": "edges",
        "removed": false,
        "selected": false,
        "selectable": true,
        "locked": false,
        "grabbable": true,
        "pannable": true,
        "classes": ""
      },
      {
        "data": {
          "source": "n26",
          "target": "n27",
          "id": "e33"
        },
        "position": {
          "x": 0,
          "y": 0
        },
        "group": "edges",
        "removed": false,
        "selected": false,
        "selectable": true,
        "locked": false,
        "grabbable": true,
        "pannable": true,
        "classes": ""
      },
      {
        "data": {
          "source": "n28",
          "target": "n26",
          "id": "e34"
        },
        "position": {
          "x": 0,
          "y": 0
        },
        "group": "edges",
        "removed": false,
        "selected": false,
        "selectable": true,
        "locked": false,
        "grabbable": true,
        "pannable": true,
        "classes": ""
      },
      {
        "data": {
          "source": "n29",
          "target": "n27",
          "id": "e35"
        },
        "position": {
          "x": 0,
          "y": 0
        },
        "group": "edges",
        "removed": false,
        "selected": false,
        "selectable": true,
        "locked": false,
        "grabbable": true,
        "pannable": true,
        "classes": ""
      },
      {
        "data": {
          "source": "n27",
          "target": "n28",
          "id": "e36"
        },
        "position": {
          "x": 0,
          "y": 0
        },
        "group": "edges",
        "removed": false,
        "selected": false,
        "selectable": true,
        "locked": false,
        "grabbable": true,
        "pannable": true,
        "classes": ""
      },
      {
        "data": {
          "source": "n28",
          "target": "n30",
          "id": "e37"
        },
        "position": {
          "x": 0,
          "y": 0
        },
        "group": "edges",
        "removed": false,
        "selected": false,
        "selectable": true,
        "locked": false,
        "grabbable": true,
        "pannable": true,
        "classes": ""
      },
      {
        "data": {
          "source": "n30",
          "target": "n31",
          "id": "e38"
        },
        "position": {
          "x": 0,
          "y": 0
        },
        "group": "edges",
        "removed": false,
        "selected": false,
        "selectable": true,
        "locked": false,
        "grabbable": true,
        "pannable": true,
        "classes": ""
      },
      {
        "data": {
          "source": "n30",
          "target": "n18",
          "id": "e39"
        },
        "position": {
          "x": 0,
          "y": 0
        },
        "group": "edges",
        "removed": false,
        "selected": false,
        "selectable": true,
        "locked": false,
        "grabbable": true,
        "pannable": true,
        "classes": ""
      }
    ]
  },
  "style": [
    {
      "selector": "node",
      "style": {
        "background-color": "rgb(173,26,102)"
      }
    },
    {
      "selector": "node:selected",
      "style": {
        "border-color": "rgb(0,0,0)",
        "border-width": "3px"
      }
    },
    {
      "selector": ":parent",
      "style": {
        "background-opacity": "0.333"
      }
    },
    {
      "selector": "edge",
      "style": {
        "width": "3px",
        "line-color": "rgb(173,26,102)"
      }
    },
    {
      "selector": "edge:selected",
      "style": {
        "line-color": "rgb(0,0,0)"
      }
    }
  ],
  "data": {},
  "zoomingEnabled": true,
  "userZoomingEnabled": true,
  "zoom": 0.7825674622311576,
  "minZoom": 1e-50,
  "maxZoom": 1e+50,
  "panningEnabled": true,
  "userPanningEnabled": true,
  "pan": {
    "x": 446.41617840905417,
    "y": 51.47607549825136
  },
  "boxSelectionEnabled": true,
  "renderer": {
    "name": "canvas"
  }
}